Metadata-Version: 1.1
Name: desciclopedia
Version: 3.4.8
Summary: desciclopedia API for Python
Home-page: https://github.com/goldsmith/Wikipedia
Author: Jonathan Goldsmith
Author-email: jhghank@gmail.com
License: MIT
Keywords: python wikipedia API
Platform: UNKNOWN
Classifier: Development Status :: 4 - Beta
Classifier: Topic :: Software Development :: Libraries
Classifier: License :: OSI Approved :: MIT License
Classifier: Programming Language :: Python
Classifier: Programming Language :: Python :: 3
